pycounts_ca/__init__.py
pycounts_ca/plotting.py
pycounts_ca/pycounts_ca.py
pycounts_ca-0.2.1.dist-info/LICENSE
pycounts_ca-0.2.1.dist-info/WHEEL
pycounts_ca-0.2.1.dist-info/METADATA
pycounts_ca-0.2.1.dist-info/RECORD
