Metadata-Version: 2.1
Name: pycounts-ca
Version: 0.2.1
Summary: Calculates word counts in a text file!
License: MIT
Author: Christopher Alexander
Requires-Python: >=3.9,<4.0
Classifier: License :: OSI Approved :: MIT License
Classifier: Programming Language :: Python :: 3
Classifier: Programming Language :: Python :: 3.10
Classifier: Programming Language :: Python :: 3.9
Requires-Dist: matplotlib (>=3.5.1,<4.0.0)
